ianalyzer_readers/__init__.py
ianalyzer_readers/conftest.py
ianalyzer_readers/extract.py
ianalyzer_readers/xml_tag.py
ianalyzer_readers/readers/__init__.py
ianalyzer_readers/readers/core.py
ianalyzer_readers/readers/csv.py
ianalyzer_readers/readers/html.py
ianalyzer_readers/readers/json.py
ianalyzer_readers/readers/rdf.py
ianalyzer_readers/readers/xlsx.py
ianalyzer_readers/readers/xml.py
ianalyzer_readers-0.4.0.dist-info/licenses/LICENSE
ianalyzer_readers-0.4.0.dist-info/METADATA
ianalyzer_readers-0.4.0.dist-info/WHEEL
ianalyzer_readers-0.4.0.dist-info/top_level.txt
ianalyzer_readers-0.4.0.dist-info/RECORD
