Metadata-Version: 2.4
Name: ianalyzer_readers
Version: 0.4.0
Summary: Utilities for extracting XML, HTML, CSV, XLSX, and RDF data with a common interface
Author-email: "Utrecht University, Centre for Digital Humanities - Research Software Lab" <cdh@uu.nl>
Maintainer-email: "Utrecht University, Centre for Digital Humanities - Research Software Lab" <cdh@uu.nl>
License: MIT
Project-URL: Repository, https://github.com/CentreForDigitalHumanities/ianalyzer-readers
Project-URL: Documentation, https://ianalyzer-readers.readthedocs.io/
Classifier: Development Status :: 2 - Pre-Alpha
Classifier: Intended Audience :: Science/Research
Classifier: License :: OSI Approved :: MIT License
Classifier: Operating System :: OS Independent
Classifier: Programming Language :: Python :: 3
Requires-Python: >=3.9
License-File: LICENSE
Requires-Dist: beautifulsoup4
Requires-Dist: lxml
Requires-Dist: openpyxl
Requires-Dist: pandas
Requires-Dist: requests
Requires-Dist: rdflib
Provides-Extra: dev
Requires-Dist: pytest; extra == "dev"
Requires-Dist: mkdocs; extra == "dev"
Requires-Dist: mkdocstrings-python; extra == "dev"
Dynamic: license-file
